{"_type":"export","__export_format":4,"__export_date":"2025-02-01T19:53:57.070Z","__export_source":"insomnia.desktop.app:v0.2.3-a","resources":[{"_id":"req_140c84c1675a4653824cc45493454642","parentId":"wrk_f79d8763c15b466db8c759341ef9bcaa","modified":1738439052189,"created":1738439006947,"url":"http://localhost:8080/donpos/order/v1/ping","name":"Ping","description":"","method":"GET","body":{},"parameters":[],"headers":[{"name":"User-Agent","value":"insomnium/0.2.3-a"}],"authentication":{},"metaSortKey":-1738439006947,"isPrivate":false,"settingStoreCookies":true,"settingSendCookies":true,"settingDisableRenderRequestBody":false,"settingEncodeUrl":true,"settingRebuildPath":true,"settingFollowRedirects":"global","segmentParams":[],"_type":"request"},{"_id":"wrk_f79d8763c15b466db8c759341ef9bcaa","parentId":null,"modified":1738438844548,"created":1738438779218,"name":"DonPosOrder","description":"","scope":"collection","_type":"workspace"},{"_id":"req_bdf6fd78adad4174a41c87feaa9da03d","parentId":"wrk_f79d8763c15b466db8c759341ef9bcaa","modified":1738439583445,"created":1738439289920,"url":"http://localhost:8080/donpos/order/v1/floors","name":"Floor","description":"","method":"GET","body":{},"parameters":[],"headers":[{"name":"User-Agent","value":"insomnium/0.2.3-a"}],"authentication":{"type":"bearer","token":"eyJhbGciOiJIUzI1NiJ9.eyJpc3MiOiJkb24tcG9zLW9yZGVyIiwic3ViIjoic2hlcmxvY2siLCJuYmYiOjE3Mzg0MzkyNzYsImV4cCI6MTczODQ0Mjg3NiwiaWF0IjoxNzM4NDM5Mjc2LCJyb2xlcyI6W119.G2bQzb7irsUXRyXEV60ZuuK6ggW4JtolTHDrpkO6DTk"},"metaSortKey":-1738438981710.5,"isPrivate":false,"settingStoreCookies":true,"settingSendCookies":true,"settingDisableRenderRequestBody":false,"settingEncodeUrl":true,"settingRebuildPath":true,"settingFollowRedirects":"global","segmentParams":[],"_type":"request"},{"_id":"req_02d3592ff2cd4548a867c94c2a51adb3","parentId":"wrk_f79d8763c15b466db8c759341ef9bcaa","modified":1738438967705,"created":1738438956473,"url":"http://localhost:8080","name":"Home","description":"","method":"GET","body":{},"parameters":[],"headers":[{"name":"Authorization","value":"Bearer eyJhbGciOiJIUzI1NiJ9.eyJpc3MiOiJkb24tcG9zLW9yZGVyIiwic3ViIjoic2hlcmxvY2siLCJuYmYiOjE3Mzg0Mzg1MjAsImV4cCI6MTczODQ0MjEyMCwiaWF0IjoxNzM4NDM4NTIwLCJyb2xlcyI6W119.f7xNgcriiEcpSujFHDh0k85ObftgltacPNUX9qFiGgs"},{"name":"User-Agent","value":"insomnia/10.3.0"}],"authentication":{},"metaSortKey":-1738438956474,"isPrivate":false,"settingStoreCookies":true,"settingSendCookies":true,"settingDisableRenderRequestBody":false,"settingEncodeUrl":true,"settingRebuildPath":true,"settingFollowRedirects":"global","segmentParams":[],"_type":"request"},{"_id":"req_8b308f66e46a43889dc95d9c8436a41b","parentId":"wrk_f79d8763c15b466db8c759341ef9bcaa","modified":1738439276383,"created":1738438880507,"url":"http://localhost:8080/login","name":"Login","description":"","method":"POST","body":{"mimeType":"application/json","text":"{\n\t\"username\": \"sherlock\",\n\t\"password\": \"password\"\n}"},"parameters":[],"headers":[{"name":"Content-Type","value":"application/json"},{"name":"User-Agent","value":"insomnia/10.3.0"}],"authentication":{},"metaSortKey":-1738438880507,"isPrivate":false,"settingStoreCookies":true,"settingSendCookies":true,"settingDisableRenderRequestBody":false,"settingEncodeUrl":true,"settingRebuildPath":true,"settingFollowRedirects":"global","segmentParams":[],"_type":"request"},{"_id":"env_649441d4ded6493091ef2bc510295648","parentId":"wrk_f79d8763c15b466db8c759341ef9bcaa","modified":1738438778217,"created":1738438778217,"name":"Base Environment","data":{},"dataPropertyOrder":null,"color":null,"isPrivate":false,"metaSortKey":1738438778217,"_type":"environment"},{"_id":"jar_05236e0988d14f169f1a1b871729f6ba","parentId":"wrk_f79d8763c15b466db8c759341ef9bcaa","modified":1738438779217,"created":1738438779217,"name":"Default Jar","cookies":[],"_type":"cookie_jar"}]}